pyvdr/__init__.py
pyvdr/pre__pyvdr.py
pyvdr/pyvdr.py
pyvdr/svdrp.py
pyvdr-0.3.1.dist-info/LICENSE
pyvdr-0.3.1.dist-info/METADATA
pyvdr-0.3.1.dist-info/WHEEL
pyvdr-0.3.1.dist-info/top_level.txt
pyvdr-0.3.1.dist-info/RECORD
