Metadata-Version: 2.1
Name: pyvdr
Version: 0.3.1
Summary: Python library for accessing a Linux VDR via SVDRP
Home-page: http://github.com/baschno/pyvdr
Author: baschno
Author-email: bastian.schnorbus@googlemail.com
License: MIT
Platform: UNKNOWN
Requires-Python: >=3.6
